classify_image_dimension/classify_image_dimension.py
classify_image_dimension-0.0.2.dist-info/DESCRIPTION.rst
classify_image_dimension-0.0.2.dist-info/METADATA
classify_image_dimension-0.0.2.dist-info/RECORD
classify_image_dimension-0.0.2.dist-info/WHEEL
classify_image_dimension-0.0.2.dist-info/entry_points.txt
classify_image_dimension-0.0.2.dist-info/metadata.json
classify_image_dimension-0.0.2.dist-info/top_level.txt
